sthree/__init__.py
sthree/bucket.py
sthree/iterate.py
sthree/models.py
sthree-0.1.2.dist-info/METADATA
sthree-0.1.2.dist-info/WHEEL
sthree-0.1.2.dist-info/top_level.txt
sthree-0.1.2.dist-info/RECORD
