Metadata-Version: 2.1
Name: sthree
Version: 0.1.2
Summary: A suite of typed data structures backed by Amazon S3.
Home-page: https://github.com/anatoly-scherbakov/sthree
Author: Anatoly Scherbakov
Author-email: altaisoft@gmail.com
License: MIT
Platform: UNKNOWN
Classifier: Programming Language :: Python :: 3
Classifier: Programming Language :: Python :: 3.7
Classifier: License :: OSI Approved :: MIT License
Classifier: Operating System :: OS Independent
Requires-Dist: boto3-type-annotations
Provides-Extra: boto
Requires-Dist: boto3 ; extra == 'boto'
Provides-Extra: dev
Requires-Dist: pytest ; extra == 'dev'
Requires-Dist: boto3 ; extra == 'dev'
Requires-Dist: moto ; extra == 'dev'
Requires-Dist: fire ; extra == 'dev'
Requires-Dist: twine ; extra == 'dev'
